{
  "dataResults": [
    {
      "titel": "Weekly Nerd 1",
      "naam_spreker": "Jan Jansen",
      "datum": 30,
      "verslag": "Software Engineer",
      "reflectie": ""
    },
    {
      "titel": "Weekly Nerd 2",
      "naam_spreker": "Jan Jansen",
      "datum": 30,
      "verslag": "Software Engineer",
      "reflectie": ""
    },
    {
      "titel": "Weekly Nerd 3",
      "naam_spreker": "Jan Jansen",
      "datum": 30,
      "verslag": "Software Engineer",
      "reflectie": ""
    },
    {
      "titel": "Weekly Nerd 4",
      "naam_spreker": "Jan Jansen",
      "datum": 30,
      "verslag": "Software Engineer",
      "reflectie": ""
    },
    {
      "titel": "Weekly Nerd 5",
      "naam_spreker": "Jan Jansen",
      "datum": 30,
      "verslag": "Software Engineer",
      "reflectie": ""
    },
    {
      "titel": "Weekly Nerd 6",
      "naam_spreker": "Jan Jansen",
      "datum": 30,
      "verslag": "Software Engineer",
      "reflectie": ""
    },
    {
      "titel": "Weekly Nerd 7",
      "naam_spreker": "Jan Jansen",
      "datum": 30,
      "verslag": "Software Engineer",
      "reflectie": ""
    },
    {
      "titel": "Weekly Nerd 8",
      "naam_spreker": "Jan Jansen",
      "datum": 30,
      "verslag": "Software Engineer",
      "reflectie": ""
    }
  ]
}